langchain_critique/__init__.py
langchain_critique/toolkits.py
langchain_critique/tools.py
langchain_critique-0.1.1.dist-info/LICENSE
langchain_critique-0.1.1.dist-info/METADATA
langchain_critique-0.1.1.dist-info/WHEEL
langchain_critique-0.1.1.dist-info/RECORD
